nokcut/__init__.py
nokcut/idx2subword.lab6
nokcut/nok1.model
nokcut/subword2idx.lab6
nokcut-0.4.dist-info/LICENSE
nokcut-0.4.dist-info/METADATA
nokcut-0.4.dist-info/WHEEL
nokcut-0.4.dist-info/top_level.txt
nokcut-0.4.dist-info/RECORD
