Metadata-Version: 2.1
Name: nokcut
Version: 0.4
Summary: Thai Word Segmentation using TCC + Bidirectional RNNs
Home-page: https://github.com/wannaphongcom/NokCut/
Author: NokCut
Author-email: wannaphong@kkumail.com
License: Apache Software License 2.0
Keywords: nokcut
Platform: UNKNOWN
Classifier: Development Status :: 5 - Production/Stable
Classifier: Programming Language :: Python :: 3
Classifier: Intended Audience :: Developers
Classifier: License :: OSI Approved :: Apache Software License
Classifier: Natural Language :: Thai
Classifier: Topic :: Text Processing :: Linguistic
Requires-Python: >=3.5
Requires-Dist: pythainlp (>=1.7)
Requires-Dist: torch
